objectproxypool/__init__.py
objectproxypool/pool.py
objectproxypool/shared_array.py
objectproxypool/shared_memory_fix.py
objectproxypool-0.0.7.dist-info/licenses/LICENSE
objectproxypool-0.0.7.dist-info/METADATA
objectproxypool-0.0.7.dist-info/WHEEL
objectproxypool-0.0.7.dist-info/top_level.txt
objectproxypool-0.0.7.dist-info/zip-safe
objectproxypool-0.0.7.dist-info/RECORD
