Metadata-Version: 2.4
Name: objectproxypool
Version: 0.0.7
Summary: Simple object-based multiprocessing
Home-page: https://git.ufz.de/oesa/objectproxypool
Author: Samuel M. Fischer
Author-email: samuel.fischer@ufz.de
License: GNU Lesser General Public License v3 (LGPLv3)
Classifier: Programming Language :: Python :: 3
Classifier: License :: OSI Approved :: GNU Lesser General Public License v3 (LGPLv3)
Classifier: Operating System :: OS Independent
License-File: LICENSE
Requires-Dist: numpy>=1.23
Requires-Dist: more_itertools
Dynamic: license-file
